glasses_detector/__init__.py
glasses_detector/__main__.py
glasses_detector/classifier.py
glasses_detector/detector.py
glasses_detector/segmenter.py
glasses_detector/utils.py
glasses_detector/_data/__init__.py
glasses_detector/_data/augmenter_mixin.py
glasses_detector/_data/base_categorized_dataset.py
glasses_detector/_data/binary_classification_dataset.py
glasses_detector/_data/binary_detection_dataset.py
glasses_detector/_data/binary_segmentation_dataset.py
glasses_detector/_wrappers/__init__.py
glasses_detector/_wrappers/binary_classifier.py
glasses_detector/_wrappers/binary_detector.py
glasses_detector/_wrappers/binary_segmenter.py
glasses_detector/_wrappers/metrics.py
glasses_detector/architectures/__init__.py
glasses_detector/architectures/tiny_binary_classifier.py
glasses_detector/architectures/tiny_binary_detector.py
glasses_detector/architectures/tiny_binary_segmenter.py
glasses_detector/components/__init__.py
glasses_detector/components/base_model.py
glasses_detector/components/pred_interface.py
glasses_detector/components/pred_type.py
glasses_detector-1.0.4.dist-info/licenses/LICENSE
glasses_detector-1.0.4.dist-info/METADATA
glasses_detector-1.0.4.dist-info/WHEEL
glasses_detector-1.0.4.dist-info/entry_points.txt
glasses_detector-1.0.4.dist-info/top_level.txt
glasses_detector-1.0.4.dist-info/RECORD
