Metadata-Version: 2.4
Name: glasses-detector
Version: 1.0.4
Summary: Glasses classification, detection, and segmentation.
Home-page: https://github.com/mantasu/glasses-detector
Author: Mantas Birškus
Author-email: mantix7@gmail.com
License: MIT
Project-URL: Documentation, https://mantasu.github.io/glasses-detector
Project-URL: Bug Tracker, https://github.com/mantasu/glasses-detector/issues
Keywords: python,pytorch,torchvision,computer,vision,image,face,eyes,transparent,opaque,glasses,googles,spectacles,eyeglasses,sunglasses,frames,lenses,legs,shadows,binary,identification,identifier,classification,classifier,segmentation,segmenter,detection,detector,cuda,mps,gpu
Classifier: Topic :: Scientific/Engineering :: Artificial Intelligence
Classifier: Topic :: Scientific/Engineering :: Image Processing
Classifier: Topic :: Scientific/Engineering :: Image Recognition
Classifier: Topic :: Software Development :: Libraries :: Python Modules
Classifier: Topic :: Software Development :: Libraries :: Application Frameworks
Classifier: Development Status :: 5 - Production/Stable
Classifier: Intended Audience :: Science/Research
Classifier: Intended Audience :: Education
Classifier: Intended Audience :: Developers
Classifier: Intended Audience :: Information Technology
Classifier: Programming Language :: Python
Classifier: Programming Language :: Python :: 3
Classifier: Programming Language :: Python :: 3.12
Classifier: Programming Language :: Python :: 3.13
Classifier: Natural Language :: English
Classifier: License :: OSI Approved :: MIT License
Classifier: Operating System :: OS Independent
Classifier: Environment :: GPU :: NVIDIA CUDA :: 12
Classifier: Environment :: Console
Classifier: Environment :: MacOS X
Classifier: Environment :: Win32 (MS Windows)
Classifier: Environment :: Other Environment
Requires-Python: >=3.12
License-File: LICENSE
Requires-Dist: tqdm
Requires-Dist: torch
Requires-Dist: torchvision
Dynamic: author
Dynamic: author-email
Dynamic: classifier
Dynamic: description
Dynamic: description-content-type
Dynamic: home-page
Dynamic: keywords
Dynamic: license
Dynamic: license-file
Dynamic: project-url
Dynamic: requires-dist
Dynamic: requires-python
Dynamic: summary
